{

    "672328094": {
        "uid": 672328094,
        "uname": "嘉然今天吃什么",
        "group": [
            655742099
        ],
        "watch": true,
        "islucky": false,
        "ad_keys": [
            "恰饭",
            "广告"
        ]
    },
    "14890801": {
        "uid": 14890801,
        "uname": "大炒面制造者Cen",
        "group": [
            655742099
        ],
        "watch": true,
        "islucky": false,
        "ad_keys": [
            "恰饭",
            "广告"
        ]
    },
    "233114659": {
        "uid": 233114659,
        "uname": "碧蓝航线",
        "group": [
            655742099
        ],
        "watch": true,
        "islucky": false,
        "ad_keys": [
            "恰饭",
            "广告"
        ]
    }
}